{"minified":"composer/2.0","packages":{"cache/array-adapter":[{"name":"cache/array-adapter","description":"A PSR-6 cache implementation using a php array. This implementation supports tags","keywords":["cache","array","tag","psr-6"],"homepage":"http://www.php-cache.com/en/latest/","version":"1.2.0","version_normalized":"1.2.0.0","license":["MIT"],"authors":[{"name":"Aaron Scherer","email":"aequasi@gmail.com","homepage":"https://github.com/aequasi"},{"name":"Tobias Nyholm","email":"tobias.nyholm@gmail.com","homepage":"https://github.com/nyholm"}],"source":{"url":"https://github.com/php-cache/array-adapter.git","type":"git","reference":"7658acf46b35a23b7be13e50a2792049e1c678c4"},"dist":{"url":"https://api.github.com/repos/php-cache/array-adapter/zipball/7658acf46b35a23b7be13e50a2792049e1c678c4","type":"zip","shasum":"","reference":"7658acf46b35a23b7be13e50a2792049e1c678c4"},"type":"library","time":"2022-01-15T15:47:19+00:00","autoload":{"psr-4":{"Cache\\Adapter\\PHPArray\\":""},"exclude-from-classmap":["/Tests/"]},"extra":{"branch-alias":{"dev-master":"1.1-dev"}},"require":{"php":">=7.4","cache/adapter-common":"^1.0","cache/hierarchical-cache":"^1.0","psr/cache":"^1.0 || ^2.0","psr/simple-cache":"^1.0"},"require-dev":{"cache/integration-tests":"^0.17","phpunit/phpunit":"^7.5.20 || ^9.5.10"},"provide":{"psr/cache-implementation":"^1.0","psr/simple-cache-implementation":"^1.0"},"support":{"source":"https://github.com/php-cache/array-adapter/tree/1.2.0"}},{"version":"1.1.0","version_normalized":"1.1.0.0","source":{"url":"https://github.com/php-cache/array-adapter.git","type":"git","reference":"71e72a51b76ed2668642a35690a7df7178f00670"},"dist":{"url":"https://api.github.com/repos/php-cache/array-adapter/zipball/71e72a51b76ed2668642a35690a7df7178f00670","type":"zip","shasum":"","reference":"71e72a51b76ed2668642a35690a7df7178f00670"},"time":"2020-12-14T12:17:39+00:00","require":{"php":"^5.6 || ^7.0 || ^8.0","cache/adapter-common":"^1.0","cache/hierarchical-cache":"^1.0","psr/cache":"^1.0","psr/simple-cache":"^1.0"},"require-dev":{"cache/integration-tests":"^0.16","phpunit/phpunit":"^5.7.21"},"support":{"source":"https://github.com/php-cache/array-adapter/tree/1.1.0"}},{"version":"1.0.1","version_normalized":"1.0.1.0","authors":[{"name":"Aaron Scherer","email":"aequasi@gmail.com","homepage":"https://github.com/aequasi"},{"name":"Tobias Nyholm","email":"tobias.nyholm@gmail.com","homepage":"https://github.com/Nyholm"}],"source":{"url":"https://github.com/php-cache/array-adapter.git","type":"git","reference":"6e9ae7f8bbf1b07bdd6144cb944059f91ae65a14"},"dist":{"url":"https://api.github.com/repos/php-cache/array-adapter/zipball/6e9ae7f8bbf1b07bdd6144cb944059f91ae65a14","type":"zip","shasum":"","reference":"6e9ae7f8bbf1b07bdd6144cb944059f91ae65a14"},"time":"2017-11-19T11:08:05+00:00","extra":{"branch-alias":{"dev-master":"1.0-dev"}},"require":{"php":"^5.6 || ^7.0","psr/cache":"^1.0","psr/simple-cache":"^1.0","cache/adapter-common":"^1.0","cache/hierarchical-cache":"^1.0"},"require-dev":{"phpunit/phpunit":"^5.7.21","cache/integration-tests":"^0.16"},"support":{"source":"https://github.com/php-cache/array-adapter/tree/master"}},{"version":"1.0.0","version_normalized":"1.0.0.0","source":{"url":"https://github.com/php-cache/array-adapter.git","type":"git","reference":"e5e2753b954e8b5edd7c431dac9be42f4b9c84aa"},"dist":{"url":"https://api.github.com/repos/php-cache/array-adapter/zipball/e5e2753b954e8b5edd7c431dac9be42f4b9c84aa","type":"zip","shasum":"","reference":"e5e2753b954e8b5edd7c431dac9be42f4b9c84aa"},"time":"2017-07-16T21:09:25+00:00","provide":{"psr/cache-implementation":"^1.0"}},{"version":"0.5.0","version_normalized":"0.5.0.0","source":{"url":"https://github.com/php-cache/array-adapter.git","type":"git","reference":"2877999aa087bbe591c8591d22dd88c530e01b9f"},"dist":{"url":"https://api.github.com/repos/php-cache/array-adapter/zipball/2877999aa087bbe591c8591d22dd88c530e01b9f","type":"zip","shasum":"","reference":"2877999aa087bbe591c8591d22dd88c530e01b9f"},"time":"2017-03-13T09:25:46+00:00","extra":{"branch-alias":{"dev-master":"0.6-dev"}},"require":{"php":"^5.6 || ^7.0","psr/cache":"^1.0","psr/simple-cache":"^1.0","cache/adapter-common":"^0.4","cache/hierarchical-cache":"^0.4"},"require-dev":{"phpunit/phpunit":"^4.0 || ^5.1","cache/integration-tests":"^0.16"}},{"version":"0.4.2","version_normalized":"0.4.2.0","source":{"url":"https://github.com/php-cache/array-adapter.git","type":"git","reference":"8fba4cc2b57aebac1390e254b1ce05d7b994d412"},"dist":{"url":"https://api.github.com/repos/php-cache/array-adapter/zipball/8fba4cc2b57aebac1390e254b1ce05d7b994d412","type":"zip","shasum":"","reference":"8fba4cc2b57aebac1390e254b1ce05d7b994d412"},"time":"2016-08-07T15:04:55+00:00","require":{"php":"^5.5 || ^7.0","psr/cache":"^1.0","cache/adapter-common":"^0.3","cache/hierarchical-cache":"^0.3","cache/taggable-cache":"^0.4"},"require-dev":{"phpunit/phpunit":"^4.0 || ^5.1","cache/integration-tests":"^0.11"},"extra":"__unset"},{"version":"0.4.1","version_normalized":"0.4.1.0","source":{"url":"https://github.com/php-cache/array-adapter.git","type":"git","reference":"0a55d8c3ae0041466a5e56180b9c70abafa6ef71"},"dist":{"url":"https://api.github.com/repos/php-cache/array-adapter/zipball/0a55d8c3ae0041466a5e56180b9c70abafa6ef71","type":"zip","shasum":"","reference":"0a55d8c3ae0041466a5e56180b9c70abafa6ef71"},"time":"2016-07-31T18:10:41+00:00","require":{"php":"^5.5 || ^7.0","psr/cache":"^1.0","cache/adapter-common":"^0.3","cache/hierarchical-cache":"^0.2","cache/taggable-cache":"^0.4"},"require-dev":{"phpunit/phpunit":"^4.0 || ^5.1","cache/integration-tests":"^0.10"}},{"homepage":"https://github.com/php-cache/array-adapter","version":"0.4.0","version_normalized":"0.4.0.0","source":{"url":"https://github.com/php-cache/array-adapter.git","type":"git","reference":"00d0c8187f61151837b5e4dbb8b24c8870050301"},"dist":{"url":"https://api.github.com/repos/php-cache/array-adapter/zipball/00d0c8187f61151837b5e4dbb8b24c8870050301","type":"zip","shasum":"","reference":"00d0c8187f61151837b5e4dbb8b24c8870050301"},"time":"2016-02-25T08:03:59+00:00","require":{"php":"^5.5|^7.0","psr/cache":"^1.0","cache/adapter-common":"^0.3","cache/hierarchical-cache":"^0.2","cache/taggable-cache":"^0.4"},"require-dev":{"phpunit/phpunit":"^4.0|^5.1","cache/integration-tests":"^0.9"}},{"version":"0.3.0","version_normalized":"0.3.0.0","source":{"url":"https://github.com/php-cache/array-adapter.git","type":"git","reference":"e5608210b0908681b331dcce3b81342b7da0ba7d"},"dist":{"url":"https://api.github.com/repos/php-cache/array-adapter/zipball/e5608210b0908681b331dcce3b81342b7da0ba7d","type":"zip","shasum":"","reference":"e5608210b0908681b331dcce3b81342b7da0ba7d"},"time":"2016-02-04T09:14:37+00:00","require":{"php":"^5.5|^7.0","psr/cache":"^1.0","cache/adapter-common":"^0.2","cache/hierarchical-cache":"^0.2","cache/taggable-cache":"^0.3"},"require-dev":{"phpunit/phpunit":"^4.0|^5.1","cache/integration-tests":"0.7.0"}},{"version":"0.2.0","version_normalized":"0.2.0.0","source":{"url":"https://github.com/php-cache/array-adapter.git","type":"git","reference":"0f29151dd1e48b8d11d1b4ab12845a4369c23839"},"dist":{"url":"https://api.github.com/repos/php-cache/array-adapter/zipball/0f29151dd1e48b8d11d1b4ab12845a4369c23839","type":"zip","shasum":"","reference":"0f29151dd1e48b8d11d1b4ab12845a4369c23839"},"time":"2016-01-11T22:26:26+00:00","autoload":{"psr-4":{"Cache\\Adapter\\PHPArray\\":"src/"}},"require":{"php":"^5.5|^7.0","psr/cache":"1.0.0","cache/adapter-common":"^0.1","cache/taggable-cache":"^0.3"},"require-dev":{"phpunit/phpunit":"^5.1|^4.0","cache/integration-tests":"^0.4"},"provide":{"psr/cache-implementation":"1.0.0"},"support":{"issues":"https://github.com/php-cache/array-adapter/issues","source":"https://github.com/php-cache/array-adapter/tree/master"}},{"version":"0.1.1","version_normalized":"0.1.1.0","source":{"url":"https://github.com/php-cache/array-adapter.git","type":"git","reference":"5c3b726b320e9dda3c8e9bdffcf8d0a4dad4c786"},"dist":{"url":"https://api.github.com/repos/php-cache/array-adapter/zipball/5c3b726b320e9dda3c8e9bdffcf8d0a4dad4c786","type":"zip","shasum":"","reference":"5c3b726b320e9dda3c8e9bdffcf8d0a4dad4c786"},"time":"2016-01-07T01:40:13+00:00","require":{"php":"^5.5|^7.0","psr/cache":"1.0.0","cache/adapter-common":"^0.1","cache/taggable-cache":"^0.2"},"require-dev":{"phpunit/phpunit":"^5.1|^4.0","cache/integration-tests":"dev-master"}},{"version":"0.1.0","version_normalized":"0.1.0.0","source":{"url":"https://github.com/php-cache/array-adapter.git","type":"git","reference":"d96d348891ea9953a4691da453f3a777f8bb1d59"},"dist":{"url":"https://api.github.com/repos/php-cache/array-adapter/zipball/d96d348891ea9953a4691da453f3a777f8bb1d59","type":"zip","shasum":"","reference":"d96d348891ea9953a4691da453f3a777f8bb1d59"},"time":"2016-01-06T23:12:26+00:00"}]},"security-advisories":[],"last-modified":"Wed, 06 Sep 2023 12:23:16 GMT"}